[
  {
    "loss": 2.6257,
    "grad_norm": 0.8707600235939026,
    "learning_rate": 0.0,
    "mean_token_accuracy": 0.5359823731705546,
    "epoch": 0.037914691943127965,
    "step": 1
  },
  {
    "loss": 2.9234,
    "grad_norm": 1.3508950471878052,
    "learning_rate": 0.00019048270524660196,
    "mean_token_accuracy": 0.4909110616685616,
    "epoch": 0.3791469194312796,
    "step": 10
  },
  {
    "loss": 2.1751,
    "grad_norm": 1.1939994096755981,
    "learning_rate": 0.00014817536741017152,
    "mean_token_accuracy": 0.5607685294933618,
    "epoch": 0.7582938388625592,
    "step": 20
  },
  {
    "loss": 1.4913,
    "grad_norm": 1.0253150463104248,
    "learning_rate": 8.746667664356956e-05,
    "mean_token_accuracy": 0.6718021808067958,
    "epoch": 1.113744075829384,
    "step": 30
  },
  {
    "loss": 1.1708,
    "grad_norm": 0.47943270206451416,
    "learning_rate": 3.154528940713113e-05,
    "mean_token_accuracy": 0.7451660502701998,
    "epoch": 1.4928909952606635,
    "step": 40
  },
  {
    "loss": 1.0687,
    "grad_norm": 0.7656137943267822,
    "learning_rate": 1.771274927131139e-06,
    "mean_token_accuracy": 0.7637839891016484,
    "epoch": 1.8720379146919433,
    "step": 50
  },
  {
    "train_runtime": 4598.8052,
    "train_samples_per_second": 0.367,
    "train_steps_per_second": 0.011,
    "total_flos": 1.7042425086124032e+16,
    "train_loss": 1.7318292810366704,
    "mean_token_accuracy": 0.7737205270677805,
    "epoch": 1.947867298578199,
    "step": 52
  },
  {
    "eval_loss": 1.1027551889419556,
    "eval_runtime": 44.307,
    "eval_samples_per_second": 1.016,
    "eval_steps_per_second": 1.016,
    "eval_mean_token_accuracy": 0.7613586399290296,
    "epoch": 1.947867298578199,
    "step": 52
  }
]